examples/__init__.py
examples/bernoulli_toy.py
examples/vae_reference.py
examples/vae/__init__.py
examples/vae/discrete_vae.py
examples/vae/normal_vae.py
examples/vae/train.py
examples/vae/vae.py
storch/__init__.py
storch/exceptions.py
storch/excluded_init.py
storch/inference.py
storch/storch.py
storch/tensor.py
storch/typing.py
storch/util.py
storch/wrappers.py
storch/method/__init__.py
storch/method/baseline.py
storch/method/method.py
storch/method/relax.py
storch/method/sampling.py
storch/nn/__init__.py
storch/nn/losses.py
storch/seq/__init__.py
storch/seq/blackbox.py
storch/seq/mdp.py
test/__init__.py
test/pyro_enum.py
test/test.py
test/test2.py
test/test_allowed.py
test/test_expect.py
storchastic-0.0.1.dist-info/LICENSE
storchastic-0.0.1.dist-info/METADATA
storchastic-0.0.1.dist-info/WHEEL
storchastic-0.0.1.dist-info/top_level.txt
storchastic-0.0.1.dist-info/RECORD
