Metadata-Version: 2.1
Name: storchastic
Version: 0.0.1
Summary: Deep Learning for PyTorch
Home-page: https://github.com/HEmile/storchastic
Author: Emile van Krieken
Author-email: e.van.krieken@vu.nl
License: UNKNOWN
Platform: UNKNOWN
Classifier: Programming Language :: Python :: 3
Classifier: License :: OSI Approved :: GNU Affero General Public License v3
Classifier: Operating System :: OS Independent
Requires-Python: >=3.6
